poliscipy/__init__.py
poliscipy/colors.py
poliscipy/plot.py
poliscipy/shapefile_utils.py
poliscipy/shapefiles/state_shapefile/__init__.py
poliscipy/shapefiles/state_shapefile/cb_2018_us_state_500k.cpg
poliscipy/shapefiles/state_shapefile/cb_2018_us_state_500k.dbf
poliscipy/shapefiles/state_shapefile/cb_2018_us_state_500k.prj
poliscipy/shapefiles/state_shapefile/cb_2018_us_state_500k.sbn
poliscipy/shapefiles/state_shapefile/cb_2018_us_state_500k.sbx
poliscipy/shapefiles/state_shapefile/cb_2018_us_state_500k.shp
poliscipy/shapefiles/state_shapefile/cb_2018_us_state_500k.shx
poliscipy/shapefiles/state_shapefile/electoral_votes.csv
poliscipy-0.1.0.dist-info/licenses/LICENSE
poliscipy-0.1.0.dist-info/METADATA
poliscipy-0.1.0.dist-info/WHEEL
poliscipy-0.1.0.dist-info/top_level.txt
poliscipy-0.1.0.dist-info/RECORD
