Metadata-Version: 2.4
Name: poliscipy
Version: 0.1.0
Summary: A Python package for political science data visualization.
Author: Ethan Olesinski
License: MIT License
Classifier: Programming Language :: Python :: 3
Classifier: License :: OSI Approved :: MIT License
Classifier: Operating System :: OS Independent
Requires-Python: >=3.9
License-File: LICENSE
Requires-Dist: geopandas
Requires-Dist: matplotlib
Requires-Dist: pandas
Dynamic: license-file
